daget/__init__.py
daget/__main__.py
daget/exceptions.py
daget/repos.py
daget/utils.py
daget-0.7.dist-info/licenses/LICENSE
daget-0.7.dist-info/METADATA
daget-0.7.dist-info/WHEEL
daget-0.7.dist-info/entry_points.txt
daget-0.7.dist-info/top_level.txt
daget-0.7.dist-info/RECORD
